tfidf_zones/__init__.py
tfidf_zones/api.py
tfidf_zones/cli.py
tfidf_zones/formatter.py
tfidf_zones/runner.py
tfidf_zones/scikit_engine.py
tfidf_zones/tfidf_engine.py
tfidf_zones/tokenizer.py
tfidf_zones/word_lists.py
tfidf_zones/zones.py
tfidf_zones-1.2.2.dist-info/METADATA
tfidf_zones-1.2.2.dist-info/WHEEL
tfidf_zones-1.2.2.dist-info/entry_points.txt
tfidf_zones-1.2.2.dist-info/RECORD
