Metadata-Version: 2.1
Name: tfidf-zones
Version: 1.2.2
Summary: TF-IDF zone analysis CLI — classify terms into too-common, goldilocks, and too-rare zones
License: MIT
Keywords: tfidf,tf-idf,nlp,text-analysis,zones
Author: Craig Trim
Author-email: craigtrim@gmail.com
Maintainer: Craig Trim
Maintainer-email: craigtrim@gmail.com
Requires-Python: >=3.11,<3.14
Classifier: Development Status :: 4 - Beta
Classifier: Intended Audience :: Developers
Classifier: Intended Audience :: Science/Research
Classifier: License :: OSI Approved :: MIT License
Classifier: Programming Language :: Python :: 3
Classifier: Programming Language :: Python :: 3.11
Classifier: Programming Language :: Python :: 3.12
Classifier: Programming Language :: Python :: 3.13
Classifier: Topic :: Scientific/Engineering :: Information Analysis
Classifier: Topic :: Text Processing :: Linguistic
Provides-Extra: scikit
Requires-Dist: rich (>=13.0,<14.0)
Requires-Dist: scikit-learn (>=1.5,<2.0) ; extra == "scikit"
Requires-Dist: wordnet-lookup (>=1.2)
